[
    {
        "center": {
            "x": 13.43061637878418,
            "y": -0.376292884349823,
            "z": 0.5561848282814026
        },
        "height": 1.7564061880111694,
        "label_class": "VEHICLE",
        "length": 4.960941791534424,
        "occlusion": 0,
        "rotation": {
            "w": -0.5577896702580973,
            "x": 0.0,
            "y": 0.0,
            "z": -0.8299823394225705
        },
        "score": 0.8899591565132141,
        "timestamp": 315966380219826000,
        "track_label_uuid": null,
        "tracked": true,
        "width": 1.974602460861206
    },
    {
        "center": {
            "x": -8.628337860107422,
            "y": -1.8074179887771606,
            "z": 0.6114900708198547
        },
        "height": 1.5568660497665405,
        "label_class": "VEHICLE",
        "length": 4.358353614807129,
        "occlusion": 0,
        "rotation": {
            "w": -0.9860577340392219,
            "x": 0.0,
            "y": 0.0,
            "z": -0.16640356108399557
        },
        "score": 0.8814870715141296,
        "timestamp": 315966380219826000,
        "track_label_uuid": null,
        "tracked": true,
        "width": 1.8319768905639648
    },
    {
        "center": {
            "x": -27.857267379760742,
            "y": -1.079015851020813,
            "z": 1.0038213729858398
        },
        "height": 1.778845191001892,
        "label_class": "VEHICLE",
        "length": 4.805715084075928,
        "occlusion": 0,
        "rotation": {
            "w": 0.1909793950765475,
            "x": 0.0,
            "y": 0.0,
            "z": -0.9815940457522122
        },
        "score": 0.8811042904853821,
        "timestamp": 315966380219826000,
        "track_label_uuid": null,
        "tracked": true,
        "width": 1.9968868494033813
    },
    {
        "center": {
            "x": 5.337942600250244,
            "y": 26.522756576538086,
            "z": -0.16172254085540771
        },
        "height": 1.5513806343078613,
        "label_class": "VEHICLE",
        "length": 4.114100456237793,
        "occlusion": 0,
        "rotation": {
            "w": -0.5470545517902127,
            "x": 0.0,
            "y": 0.0,
            "z": -0.8370969581629177
        },
        "score": 0.8590101003646851,
        "timestamp": 315966380219826000,
        "track_label_uuid": null,
        "tracked": true,
        "width": 1.7768876552581787
    },
    {
        "center": {
            "x": 10.55385971069336,
            "y": -12.363811492919922,
            "z": 0.5681681036949158
        },
        "height": 1.4126710891723633,
        "label_class": "VEHICLE",
        "length": 4.289356708526611,
        "occlusion": 0,
        "rotation": {
            "w": 0.8319709454100507,
            "x": 0.0,
            "y": 0.0,
            "z": -0.5548192011759384
        },
        "score": 0.8284814357757568,
        "timestamp": 315966380219826000,
        "track_label_uuid": null,
        "tracked": true,
        "width": 1.823699712753296
    },
    {
        "center": {
            "x": 14.77117919921875,
            "y": -23.500877380371094,
            "z": 1.079442024230957
        },
        "height": 1.6712154150009155,
        "label_class": "VEHICLE",
        "length": 4.134762287139893,
        "occlusion": 0,
        "rotation": {
            "w": 0.7977105231756025,
            "x": 0.0,
            "y": 0.0,
            "z": -0.6030405634904724
        },
        "score": 0.7885751128196716,
        "timestamp": 315966380219826000,
        "track_label_uuid": null,
        "tracked": true,
        "width": 1.8759448528289795
    },
    {
        "center": {
            "x": -1.417083740234375,
            "y": 25.750917434692383,
            "z": 0.03334230184555054
        },
        "height": 1.5215346813201904,
        "label_class": "VEHICLE",
        "length": 4.334324359893799,
        "occlusion": 0,
        "rotation": {
            "w": 0.8381323231453698,
            "x": 0.0,
            "y": 0.0,
            "z": -0.5454669640766023
        },
        "score": 0.7709499597549438,
        "timestamp": 315966380219826000,
        "track_label_uuid": null,
        "tracked": true,
        "width": 1.822296142578125
    },
    {
        "center": {
            "x": -33.66155242919922,
            "y": -3.53875732421875,
            "z": 0.8356067538261414
        },
        "height": 1.5857917070388794,
        "label_class": "VEHICLE",
        "length": 4.344860553741455,
        "occlusion": 0,
        "rotation": {
            "w": 0.2267032827959588,
            "x": 0.0,
            "y": 0.0,
            "z": -0.973963870772184
        },
        "score": 0.7410046458244324,
        "timestamp": 315966380219826000,
        "track_label_uuid": null,
        "tracked": true,
        "width": 1.7439405918121338
    },
    {
        "center": {
            "x": -16.208892822265625,
            "y": -4.2865891456604,
            "z": 0.7648374438285828
        },
        "height": 1.5555965900421143,
        "label_class": "VEHICLE",
        "length": 4.467267036437988,
        "occlusion": 0,
        "rotation": {
            "w": -0.9842895802990723,
            "x": 0.0,
            "y": 0.0,
            "z": -0.17656166660596528
        },
        "score": 0.6697410941123962,
        "timestamp": 315966380219826000,
        "track_label_uuid": null,
        "tracked": true,
        "width": 1.8751585483551025
    },
    {
        "center": {
            "x": 17.228641510009766,
            "y": 12.201895713806152,
            "z": 0.33625465631484985
        },
        "height": 1.808772087097168,
        "label_class": "VEHICLE",
        "length": 5.590890407562256,
        "occlusion": 0,
        "rotation": {
            "w": 0.07015770042063199,
            "x": 0.0,
            "y": 0.0,
            "z": -0.9975359126726661
        },
        "score": 0.6605927348136902,
        "timestamp": 315966380219826000,
        "track_label_uuid": null,
        "tracked": true,
        "width": 2.2880544662475586
    },
    {
        "center": {
            "x": -9.939313888549805,
            "y": 38.99085235595703,
            "z": -0.10876137018203735
        },
        "height": 1.6440708637237549,
        "label_class": "VEHICLE",
        "length": 4.275721073150635,
        "occlusion": 0,
        "rotation": {
            "w": 0.8134323869187706,
            "x": 0.0,
            "y": 0.0,
            "z": -0.5816594810639911
        },
        "score": 0.6589731574058533,
        "timestamp": 315966380219826000,
        "track_label_uuid": null,
        "tracked": true,
        "width": 1.846907377243042
    },
    {
        "center": {
            "x": 2.3353874683380127,
            "y": 33.46370315551758,
            "z": -0.3109295964241028
        },
        "height": 1.657321810722351,
        "label_class": "VEHICLE",
        "length": 4.460258483886719,
        "occlusion": 0,
        "rotation": {
            "w": -0.5165201706635726,
            "x": 0.0,
            "y": 0.0,
            "z": -0.8562750219979991
        },
        "score": 0.6482917070388794,
        "timestamp": 315966380219826000,
        "track_label_uuid": null,
        "tracked": true,
        "width": 1.9005413055419922
    },
    {
        "center": {
            "x": -39.56190490722656,
            "y": -6.017709255218506,
            "z": 0.929007351398468
        },
        "height": 1.8159774541854858,
        "label_class": "VEHICLE",
        "length": 4.837546348571777,
        "occlusion": 0,
        "rotation": {
            "w": 0.21148565700286676,
            "x": 0.0,
            "y": 0.0,
            "z": -0.9773811011484035
        },
        "score": 0.6314681768417358,
        "timestamp": 315966380219826000,
        "track_label_uuid": null,
        "tracked": true,
        "width": 1.968342900276184
    },
    {
        "center": {
            "x": -7.952931880950928,
            "y": 34.40226364135742,
            "z": -0.23345690965652466
        },
        "height": 1.563840627670288,
        "label_class": "VEHICLE",
        "length": 4.172811985015869,
        "occlusion": 0,
        "rotation": {
            "w": 0.8084846895628427,
            "x": 0.0,
            "y": 0.0,
            "z": -0.5885172102347337
        },
        "score": 0.5872805714607239,
        "timestamp": 315966380219826000,
        "track_label_uuid": null,
        "tracked": true,
        "width": 1.8489495515823364
    },
    {
        "center": {
            "x": -57.16966247558594,
            "y": -24.520475387573242,
            "z": 1.5103402137756348
        },
        "height": 1.7616304159164429,
        "label_class": "VEHICLE",
        "length": 4.703117370605469,
        "occlusion": 0,
        "rotation": {
            "w": -0.9768323427686989,
            "x": 0.0,
            "y": 0.0,
            "z": -0.21400601421692605
        },
        "score": 0.5539845824241638,
        "timestamp": 315966380219826000,
        "track_label_uuid": null,
        "tracked": true,
        "width": 2.1702041625976562
    },
    {
        "center": {
            "x": -5.967592239379883,
            "y": 53.1430549621582,
            "z": -0.35982680320739746
        },
        "height": 1.6562790870666504,
        "label_class": "VEHICLE",
        "length": 4.376010894775391,
        "occlusion": 0,
        "rotation": {
            "w": -0.5905465109481287,
            "x": 0.0,
            "y": 0.0,
            "z": -0.8070036049529096
        },
        "score": 0.5538755655288696,
        "timestamp": 315966380219826000,
        "track_label_uuid": null,
        "tracked": true,
        "width": 1.9070309400558472
    },
    {
        "center": {
            "x": -38.97120666503906,
            "y": -13.81914234161377,
            "z": 1.2315988540649414
        },
        "height": 1.603777527809143,
        "label_class": "VEHICLE",
        "length": 4.2369818687438965,
        "occlusion": 0,
        "rotation": {
            "w": -0.980701778229642,
            "x": 0.0,
            "y": 0.0,
            "z": -0.1955096472740363
        },
        "score": 0.5290564894676208,
        "timestamp": 315966380219826000,
        "track_label_uuid": null,
        "tracked": true,
        "width": 1.988900899887085
    },
    {
        "center": {
            "x": 17.99833869934082,
            "y": -39.54792022705078,
            "z": 1.4727458953857422
        },
        "height": 1.7150856256484985,
        "label_class": "VEHICLE",
        "length": 4.645637035369873,
        "occlusion": 0,
        "rotation": {
            "w": 0.8203158719937668,
            "x": 0.0,
            "y": 0.0,
            "z": -0.5719107186922676
        },
        "score": 0.4999176263809204,
        "timestamp": 315966380219826000,
        "track_label_uuid": null,
        "tracked": true,
        "width": 2.0716841220855713
    },
    {
        "center": {
            "x": -1.3491142988204956,
            "y": 43.04316329956055,
            "z": -0.34955865144729614
        },
        "height": 1.7598930597305298,
        "label_class": "VEHICLE",
        "length": 4.412359714508057,
        "occlusion": 0,
        "rotation": {
            "w": -0.5464121441173216,
            "x": 0.0,
            "y": 0.0,
            "z": -0.8375164289499707
        },
        "score": 0.4956521987915039,
        "timestamp": 315966380219826000,
        "track_label_uuid": null,
        "tracked": true,
        "width": 1.9718616008758545
    },
    {
        "center": {
            "x": 24.371179580688477,
            "y": -47.171173095703125,
            "z": 1.5657017230987549
        },
        "height": 1.6562249660491943,
        "label_class": "VEHICLE",
        "length": 4.156567096710205,
        "occlusion": 0,
        "rotation": {
            "w": 0.8148519891564505,
            "x": 0.0,
            "y": 0.0,
            "z": -0.579669074358617
        },
        "score": 0.48267629742622375,
        "timestamp": 315966380219826000,
        "track_label_uuid": null,
        "tracked": true,
        "width": 1.9418134689331055
    },
    {
        "center": {
            "x": -47.37506866455078,
            "y": -9.239232063293457,
            "z": 0.7807909846305847
        },
        "height": 1.6490131616592407,
        "label_class": "VEHICLE",
        "length": 4.300120830535889,
        "occlusion": 0,
        "rotation": {
            "w": 0.16872276010087325,
            "x": 0.0,
            "y": 0.0,
            "z": -0.9856635481866737
        },
        "score": 0.4607836604118347,
        "timestamp": 315966380219826000,
        "track_label_uuid": null,
        "tracked": true,
        "width": 1.7427263259887695
    },
    {
        "center": {
            "x": 16.52145004272461,
            "y": -7.120080471038818,
            "z": 0.7005857825279236
        },
        "height": 1.7540351152420044,
        "label_class": "VEHICLE",
        "length": 5.696676731109619,
        "occlusion": 0,
        "rotation": {
            "w": -0.5648572230859893,
            "x": 0.0,
            "y": 0.0,
            "z": -0.8251886557191543
        },
        "score": 0.39216870069503784,
        "timestamp": 315966380219826000,
        "track_label_uuid": null,
        "tracked": true,
        "width": 2.2256903648376465
    },
    {
        "center": {
            "x": -14.80244255065918,
            "y": 52.310482025146484,
            "z": -0.6390572786331177
        },
        "height": 1.7100557088851929,
        "label_class": "VEHICLE",
        "length": 4.666131496429443,
        "occlusion": 0,
        "rotation": {
            "w": 0.7977411464507933,
            "x": 0.0,
            "y": 0.0,
            "z": -0.6030000524538733
        },
        "score": 0.3613322079181671,
        "timestamp": 315966380219826000,
        "track_label_uuid": null,
        "tracked": true,
        "width": 1.9187359809875488
    },
    {
        "center": {
            "x": 29.107423782348633,
            "y": -32.49947738647461,
            "z": 1.2026135921478271
        },
        "height": 1.6421531438827515,
        "label_class": "VEHICLE",
        "length": 4.321290493011475,
        "occlusion": 0,
        "rotation": {
            "w": -0.5821053639735645,
            "x": 0.0,
            "y": 0.0,
            "z": -0.8131133655482512
        },
        "score": 0.354744017124176,
        "timestamp": 315966380219826000,
        "track_label_uuid": null,
        "tracked": true,
        "width": 1.912394404411316
    },
    {
        "center": {
            "x": -67.11922454833984,
            "y": -17.064388275146484,
            "z": 1.1831364631652832
        },
        "height": 1.7454006671905518,
        "label_class": "VEHICLE",
        "length": 4.4370222091674805,
        "occlusion": 0,
        "rotation": {
            "w": 0.1588633350819689,
            "x": 0.0,
            "y": 0.0,
            "z": -0.9873005827845105
        },
        "score": 0.3450647294521332,
        "timestamp": 315966380219826000,
        "track_label_uuid": null,
        "tracked": true,
        "width": 1.9839036464691162
    },
    {
        "center": {
            "x": -47.485713958740234,
            "y": -14.828667640686035,
            "z": 0.7463617920875549
        },
        "height": 1.506476640701294,
        "label_class": "VEHICLE",
        "length": 4.190509796142578,
        "occlusion": 0,
        "rotation": {
            "w": -0.9787771990440878,
            "x": 0.0,
            "y": 0.0,
            "z": -0.20492729108493607
        },
        "score": 0.3258155882358551,
        "timestamp": 315966380219826000,
        "track_label_uuid": null,
        "tracked": true,
        "width": 1.8603150844573975
    },
    {
        "center": {
            "x": 20.48306655883789,
            "y": -38.352657318115234,
            "z": 1.131525993347168
        },
        "height": 1.6001688241958618,
        "label_class": "VEHICLE",
        "length": 4.048253536224365,
        "occlusion": 0,
        "rotation": {
            "w": -0.5885341478926075,
            "x": 0.0,
            "y": 0.0,
            "z": -0.8084723599260042
        },
        "score": 0.3165503442287445,
        "timestamp": 315966380219826000,
        "track_label_uuid": null,
        "tracked": true,
        "width": 1.8527119159698486
    },
    {
        "center": {
            "x": -25.223072052001953,
            "y": 61.784725189208984,
            "z": -0.6096917390823364
        },
        "height": 1.7387902736663818,
        "label_class": "VEHICLE",
        "length": 4.313282489776611,
        "occlusion": 0,
        "rotation": {
            "w": 0.7879814879944697,
            "x": 0.0,
            "y": 0.0,
            "z": -0.6156989317661851
        },
        "score": 0.2959466576576233,
        "timestamp": 315966380219826000,
        "track_label_uuid": null,
        "tracked": true,
        "width": 1.9402577877044678
    },
    {
        "center": {
            "x": 24.5067138671875,
            "y": -32.11536407470703,
            "z": 1.4560253620147705
        },
        "height": 1.802706241607666,
        "label_class": "VEHICLE",
        "length": 5.246591567993164,
        "occlusion": 0,
        "rotation": {
            "w": 0.7234291532573911,
            "x": 0.0,
            "y": 0.0,
            "z": -0.6903986241420923
        },
        "score": 0.29504773020744324,
        "timestamp": 315966380219826000,
        "track_label_uuid": null,
        "tracked": true,
        "width": 2.344240665435791
    },
    {
        "center": {
            "x": -51.77751541137695,
            "y": -16.302953720092773,
            "z": 0.6354590058326721
        },
        "height": 1.5710710287094116,
        "label_class": "VEHICLE",
        "length": 4.228174209594727,
        "occlusion": 0,
        "rotation": {
            "w": -0.9917974018396725,
            "x": 0.0,
            "y": 0.0,
            "z": -0.12781984863109175
        },
        "score": 0.28372475504875183,
        "timestamp": 315966380219826000,
        "track_label_uuid": null,
        "tracked": true,
        "width": 1.8972609043121338
    },
    {
        "center": {
            "x": 44.89651107788086,
            "y": 23.51968002319336,
            "z": 0.10452479124069214
        },
        "height": 1.6930606365203857,
        "label_class": "VEHICLE",
        "length": 4.585707664489746,
        "occlusion": 0,
        "rotation": {
            "w": 0.22796376649910394,
            "x": 0.0,
            "y": 0.0,
            "z": -0.9736696160215446
        },
        "score": 0.27683302760124207,
        "timestamp": 315966380219826000,
        "track_label_uuid": null,
        "tracked": true,
        "width": 1.9740957021713257
    },
    {
        "center": {
            "x": -14.005414962768555,
            "y": 58.78147888183594,
            "z": -0.2339586615562439
        },
        "height": 1.5998520851135254,
        "label_class": "VEHICLE",
        "length": 4.083700656890869,
        "occlusion": 0,
        "rotation": {
            "w": 0.7244290867150494,
            "x": 0.0,
            "y": 0.0,
            "z": -0.6893493296734244
        },
        "score": 0.26442718505859375,
        "timestamp": 315966380219826000,
        "track_label_uuid": null,
        "tracked": true,
        "width": 1.8117812871932983
    },
    {
        "center": {
            "x": -56.53824996948242,
            "y": -21.161922454833984,
            "z": 1.242659091949463
        },
        "height": 1.591895580291748,
        "label_class": "VEHICLE",
        "length": 4.189666271209717,
        "occlusion": 0,
        "rotation": {
            "w": 0.1476430839040395,
            "x": 0.0,
            "y": 0.0,
            "z": -0.9890407068343066
        },
        "score": 0.2576005160808563,
        "timestamp": 315966380219826000,
        "track_label_uuid": null,
        "tracked": true,
        "width": 1.7956452369689941
    },
    {
        "center": {
            "x": -73.20838928222656,
            "y": -29.14006805419922,
            "z": 0.6780886054039001
        },
        "height": 1.7152808904647827,
        "label_class": "VEHICLE",
        "length": 4.224531173706055,
        "occlusion": 0,
        "rotation": {
            "w": -0.9755756777199422,
            "x": 0.0,
            "y": 0.0,
            "z": -0.21966359971846802
        },
        "score": 0.2523522973060608,
        "timestamp": 315966380219826000,
        "track_label_uuid": null,
        "tracked": true,
        "width": 2.021651268005371
    },
    {
        "center": {
            "x": 40.3913688659668,
            "y": -62.339569091796875,
            "z": 1.315068244934082
        },
        "height": 1.6494128704071045,
        "label_class": "VEHICLE",
        "length": 4.247072696685791,
        "occlusion": 0,
        "rotation": {
            "w": 0.7712124756622611,
            "x": 0.0,
            "y": 0.0,
            "z": -0.6365778172249534
        },
        "score": 0.24559593200683594,
        "timestamp": 315966380219826000,
        "track_label_uuid": null,
        "tracked": true,
        "width": 1.955967664718628
    },
    {
        "center": {
            "x": -73.22967529296875,
            "y": -19.60230255126953,
            "z": 1.0789473056793213
        },
        "height": 1.6781305074691772,
        "label_class": "VEHICLE",
        "length": 4.219080448150635,
        "occlusion": 0,
        "rotation": {
            "w": -0.9864689115413605,
            "x": 0.0,
            "y": 0.0,
            "z": -0.16394842653225905
        },
        "score": 0.23925136029720306,
        "timestamp": 315966380219826000,
        "track_label_uuid": null,
        "tracked": true,
        "width": 1.7575900554656982
    },
    {
        "center": {
            "x": -54.030235290527344,
            "y": -11.591830253601074,
            "z": 0.8370429873466492
        },
        "height": 1.6704277992248535,
        "label_class": "VEHICLE",
        "length": 4.195890426635742,
        "occlusion": 0,
        "rotation": {
            "w": -0.9872108941456623,
            "x": 0.0,
            "y": 0.0,
            "z": -0.15941973052330097
        },
        "score": 0.22967687249183655,
        "timestamp": 315966380219826000,
        "track_label_uuid": null,
        "tracked": true,
        "width": 1.799422264099121
    },
    {
        "center": {
            "x": -13.139575958251953,
            "y": 79.09827423095703,
            "z": -1.1906746625900269
        },
        "height": 1.6745576858520508,
        "label_class": "VEHICLE",
        "length": 4.244414806365967,
        "occlusion": 0,
        "rotation": {
            "w": 0.760064496798344,
            "x": 0.0,
            "y": 0.0,
            "z": -0.6498476442264604
        },
        "score": 0.2028609961271286,
        "timestamp": 315966380219826000,
        "track_label_uuid": null,
        "tracked": true,
        "width": 1.9595670700073242
    },
    {
        "center": {
            "x": -86.27090454101562,
            "y": -26.782012939453125,
            "z": 0.7090715765953064
        },
        "height": 1.7437849044799805,
        "label_class": "VEHICLE",
        "length": 4.372012615203857,
        "occlusion": 0,
        "rotation": {
            "w": 0.16744750654594165,
            "x": 0.0,
            "y": 0.0,
            "z": -0.9858809930978215
        },
        "score": 0.19767922163009644,
        "timestamp": 315966380219826000,
        "track_label_uuid": null,
        "tracked": true,
        "width": 2.0419604778289795
    },
    {
        "center": {
            "x": -68.20899200439453,
            "y": -30.741920471191406,
            "z": 1.0461485385894775
        },
        "height": 1.624105453491211,
        "label_class": "VEHICLE",
        "length": 4.173274993896484,
        "occlusion": 0,
        "rotation": {
            "w": -0.9864146420626843,
            "x": 0.0,
            "y": 0.0,
            "z": -0.16427462958213157
        },
        "score": 0.19610139727592468,
        "timestamp": 315966380219826000,
        "track_label_uuid": null,
        "tracked": true,
        "width": 1.863112449645996
    },
    {
        "center": {
            "x": 31.563213348388672,
            "y": -69.17620086669922,
            "z": 2.4956066608428955
        },
        "height": 1.6704747676849365,
        "label_class": "VEHICLE",
        "length": 4.280040264129639,
        "occlusion": 0,
        "rotation": {
            "w": 0.8426492762784138,
            "x": 0.0,
            "y": 0.0,
            "z": -0.5384628094747729
        },
        "score": 0.19552332162857056,
        "timestamp": 315966380219826000,
        "track_label_uuid": null,
        "tracked": true,
        "width": 1.986528992652893
    },
    {
        "center": {
            "x": -77.36198425292969,
            "y": -24.441347122192383,
            "z": 1.2763144969940186
        },
        "height": 1.6690163612365723,
        "label_class": "VEHICLE",
        "length": 4.2918009757995605,
        "occlusion": 0,
        "rotation": {
            "w": -0.9894954686567352,
            "x": 0.0,
            "y": 0.0,
            "z": -0.1445638872878979
        },
        "score": 0.1628456562757492,
        "timestamp": 315966380219826000,
        "track_label_uuid": null,
        "tracked": true,
        "width": 1.8645144701004028
    },
    {
        "center": {
            "x": -3.7156476974487305,
            "y": 48.30345153808594,
            "z": -0.4438413381576538
        },
        "height": 1.5207916498184204,
        "label_class": "VEHICLE",
        "length": 3.983703851699829,
        "occlusion": 0,
        "rotation": {
            "w": 0.7650770745837953,
            "x": 0.0,
            "y": 0.0,
            "z": -0.6439387159864686
        },
        "score": 0.1569395661354065,
        "timestamp": 315966380219826000,
        "track_label_uuid": null,
        "tracked": true,
        "width": 1.7375555038452148
    },
    {
        "center": {
            "x": 64.35542297363281,
            "y": 39.05254364013672,
            "z": -0.20182478427886963
        },
        "height": 1.7261874675750732,
        "label_class": "VEHICLE",
        "length": 4.570652484893799,
        "occlusion": 0,
        "rotation": {
            "w": 0.6885730894820754,
            "x": 0.0,
            "y": 0.0,
            "z": -0.7251669465999604
        },
        "score": 0.15055128931999207,
        "timestamp": 315966380219826000,
        "track_label_uuid": null,
        "tracked": true,
        "width": 1.910652995109558
    },
    {
        "center": {
            "x": 66.77583312988281,
            "y": 42.040283203125,
            "z": -0.19822561740875244
        },
        "height": 1.5859510898590088,
        "label_class": "VEHICLE",
        "length": 4.461964130401611,
        "occlusion": 0,
        "rotation": {
            "w": 0.16387032642493823,
            "x": 0.0,
            "y": 0.0,
            "z": -0.9864818883879137
        },
        "score": 0.1476462185382843,
        "timestamp": 315966380219826000,
        "track_label_uuid": null,
        "tracked": true,
        "width": 1.8595038652420044
    },
    {
        "center": {
            "x": -52.422122955322266,
            "y": -10.032448768615723,
            "z": 1.03666090965271
        },
        "height": 1.783811330795288,
        "label_class": "VEHICLE",
        "length": 4.40679407119751,
        "occlusion": 0,
        "rotation": {
            "w": -0.9669784130430681,
            "x": 0.0,
            "y": 0.0,
            "z": -0.25485829142625444
        },
        "score": 0.1476089358329773,
        "timestamp": 315966380219826000,
        "track_label_uuid": null,
        "tracked": true,
        "width": 1.8532781600952148
    },
    {
        "center": {
            "x": -6.797327995300293,
            "y": 56.36317825317383,
            "z": -0.6558821201324463
        },
        "height": 1.566881775856018,
        "label_class": "VEHICLE",
        "length": 4.150174140930176,
        "occlusion": 0,
        "rotation": {
            "w": -0.6418186072537959,
            "x": 0.0,
            "y": 0.0,
            "z": -0.7668564894312349
        },
        "score": 0.1443939507007599,
        "timestamp": 315966380219826000,
        "track_label_uuid": null,
        "tracked": true,
        "width": 1.8137134313583374
    },
    {
        "center": {
            "x": -93.04877471923828,
            "y": -36.455562591552734,
            "z": 1.0398788452148438
        },
        "height": 1.6884466409683228,
        "label_class": "VEHICLE",
        "length": 4.3878092765808105,
        "occlusion": 0,
        "rotation": {
            "w": -0.9894138667765419,
            "x": 0.0,
            "y": 0.0,
            "z": -0.14512132934304142
        },
        "score": 0.1434990018606186,
        "timestamp": 315966380219826000,
        "track_label_uuid": null,
        "tracked": true,
        "width": 1.994402289390564
    },
    {
        "center": {
            "x": -17.252273559570312,
            "y": 97.72315216064453,
            "z": -1.05484938621521
        },
        "height": 1.7069307565689087,
        "label_class": "VEHICLE",
        "length": 4.6646318435668945,
        "occlusion": 0,
        "rotation": {
            "w": 0.7889500761947119,
            "x": 0.0,
            "y": 0.0,
            "z": -0.614457303050715
        },
        "score": 0.1409909576177597,
        "timestamp": 315966380219826000,
        "track_label_uuid": null,
        "tracked": true,
        "width": 1.9920700788497925
    },
    {
        "center": {
            "x": 68.60565948486328,
            "y": 33.35820770263672,
            "z": -0.15205615758895874
        },
        "height": 1.7917685508728027,
        "label_class": "VEHICLE",
        "length": 4.908856391906738,
        "occlusion": 0,
        "rotation": {
            "w": -0.9993140538777584,
            "x": 0.0,
            "y": 0.0,
            "z": -0.03703271151833838
        },
        "score": 0.14091543853282928,
        "timestamp": 315966380219826000,
        "track_label_uuid": null,
        "tracked": true,
        "width": 2.146078109741211
    },
    {
        "center": {
            "x": 39.36942672729492,
            "y": -55.64148712158203,
            "z": 1.3275134563446045
        },
        "height": 1.6788727045059204,
        "label_class": "VEHICLE",
        "length": 4.362112045288086,
        "occlusion": 0,
        "rotation": {
            "w": 0.09722612687058312,
            "x": 0.0,
            "y": 0.0,
            "z": -0.9952623173082287
        },
        "score": 0.13849422335624695,
        "timestamp": 315966380219826000,
        "track_label_uuid": null,
        "tracked": true,
        "width": 2.0032875537872314
    },
    {
        "center": {
            "x": 96.1129150390625,
            "y": 55.57090759277344,
            "z": 1.096130609512329
        },
        "height": 1.7441571950912476,
        "label_class": "VEHICLE",
        "length": 4.606334686279297,
        "occlusion": 0,
        "rotation": {
            "w": -0.9860235939293326,
            "x": 0.0,
            "y": 0.0,
            "z": -0.16660573884078128
        },
        "score": 0.13747215270996094,
        "timestamp": 315966380219826000,
        "track_label_uuid": null,
        "tracked": true,
        "width": 2.1652636528015137
    },
    {
        "center": {
            "x": 37.21010208129883,
            "y": -57.28876876831055,
            "z": 1.2079894542694092
        },
        "height": 1.6527482271194458,
        "label_class": "VEHICLE",
        "length": 4.344866752624512,
        "occlusion": 0,
        "rotation": {
            "w": 0.6611932331312689,
            "x": 0.0,
            "y": 0.0,
            "z": -0.7502156413068309
        },
        "score": 0.1355213075876236,
        "timestamp": 315966380219826000,
        "track_label_uuid": null,
        "tracked": true,
        "width": 1.9508721828460693
    },
    {
        "center": {
            "x": -65.21660614013672,
            "y": -29.940689086914062,
            "z": 1.1845686435699463
        },
        "height": 1.7300418615341187,
        "label_class": "VEHICLE",
        "length": 4.550717830657959,
        "occlusion": 0,
        "rotation": {
            "w": -0.9790660970456625,
            "x": 0.0,
            "y": 0.0,
            "z": -0.20354256954203306
        },
        "score": 0.13440580666065216,
        "timestamp": 315966380219826000,
        "track_label_uuid": null,
        "tracked": true,
        "width": 1.9420706033706665
    },
    {
        "center": {
            "x": -58.84571075439453,
            "y": -32.95934295654297,
            "z": 1.3993079662322998
        },
        "height": 1.615826964378357,
        "label_class": "VEHICLE",
        "length": 4.264730930328369,
        "occlusion": 0,
        "rotation": {
            "w": -0.5853235341708335,
            "x": 0.0,
            "y": 0.0,
            "z": -0.8107998275442374
        },
        "score": 0.13337092101573944,
        "timestamp": 315966380219826000,
        "track_label_uuid": null,
        "tracked": true,
        "width": 1.782199501991272
    },
    {
        "center": {
            "x": 15.903844833374023,
            "y": -19.46829605102539,
            "z": 0.6520403027534485
        },
        "height": 1.5763506889343262,
        "label_class": "VEHICLE",
        "length": 4.18538761138916,
        "occlusion": 0,
        "rotation": {
            "w": -0.9954801870428568,
            "x": 0.0,
            "y": 0.0,
            "z": -0.09496945406349819
        },
        "score": 0.12842614948749542,
        "timestamp": 315966380219826000,
        "track_label_uuid": null,
        "tracked": true,
        "width": 1.7826510667800903
    },
    {
        "center": {
            "x": -81.24378204345703,
            "y": -23.53939437866211,
            "z": 0.8477385640144348
        },
        "height": 1.747989535331726,
        "label_class": "VEHICLE",
        "length": 4.368950366973877,
        "occlusion": 0,
        "rotation": {
            "w": -0.9875418464117717,
            "x": 0.0,
            "y": 0.0,
            "z": -0.15735660642511545
        },
        "score": 0.12780040502548218,
        "timestamp": 315966380219826000,
        "track_label_uuid": null,
        "tracked": true,
        "width": 1.9314578771591187
    },
    {
        "center": {
            "x": -31.577438354492188,
            "y": 77.08245086669922,
            "z": -0.5490474104881287
        },
        "height": 1.6013691425323486,
        "label_class": "VEHICLE",
        "length": 4.187023639678955,
        "occlusion": 0,
        "rotation": {
            "w": 0.7362103652140507,
            "x": 0.0,
            "y": 0.0,
            "z": -0.6767527599880137
        },
        "score": 0.12486505508422852,
        "timestamp": 315966380219826000,
        "track_label_uuid": null,
        "tracked": true,
        "width": 1.942073106765747
    },
    {
        "center": {
            "x": 74.00141906738281,
            "y": 36.35729217529297,
            "z": 0.16634076833724976
        },
        "height": 1.796883225440979,
        "label_class": "VEHICLE",
        "length": 4.639791965484619,
        "occlusion": 0,
        "rotation": {
            "w": -0.993856666401541,
            "x": 0.0,
            "y": 0.0,
            "z": -0.11067486909509325
        },
        "score": 0.12406068295240402,
        "timestamp": 315966380219826000,
        "track_label_uuid": null,
        "tracked": true,
        "width": 2.0592739582061768
    },
    {
        "center": {
            "x": 27.636545181274414,
            "y": -29.46929359436035,
            "z": 1.311781406402588
        },
        "height": 1.6825615167617798,
        "label_class": "VEHICLE",
        "length": 4.357579708099365,
        "occlusion": 0,
        "rotation": {
            "w": -0.5492980495133554,
            "x": 0.0,
            "y": 0.0,
            "z": -0.8356265031704196
        },
        "score": 0.12217395007610321,
        "timestamp": 315966380219826000,
        "track_label_uuid": null,
        "tracked": true,
        "width": 1.9166401624679565
    },
    {
        "center": {
            "x": -22.781017303466797,
            "y": 65.40180206298828,
            "z": -0.8190558552742004
        },
        "height": 1.6129177808761597,
        "label_class": "VEHICLE",
        "length": 4.214715480804443,
        "occlusion": 0,
        "rotation": {
            "w": 0.6630002025896075,
            "x": 0.0,
            "y": 0.0,
            "z": -0.7486192165354423
        },
        "score": 0.11845617741346359,
        "timestamp": 315966380219826000,
        "track_label_uuid": null,
        "tracked": true,
        "width": 1.874792456626892
    },
    {
        "center": {
            "x": 28.378374099731445,
            "y": -61.03416442871094,
            "z": 2.188140869140625
        },
        "height": 1.6654869318008423,
        "label_class": "VEHICLE",
        "length": 4.344654083251953,
        "occlusion": 0,
        "rotation": {
            "w": 0.8238934703474105,
            "x": 0.0,
            "y": 0.0,
            "z": -0.5667446951837315
        },
        "score": 0.11790196597576141,
        "timestamp": 315966380219826000,
        "track_label_uuid": null,
        "tracked": true,
        "width": 2.0822336673736572
    },
    {
        "center": {
            "x": 71.63526153564453,
            "y": 39.65932083129883,
            "z": 0.5432857871055603
        },
        "height": 1.682325839996338,
        "label_class": "VEHICLE",
        "length": 4.329576015472412,
        "occlusion": 0,
        "rotation": {
            "w": 0.1368611659595911,
            "x": 0.0,
            "y": 0.0,
            "z": -0.9905902388233903
        },
        "score": 0.11746855080127716,
        "timestamp": 315966380219826000,
        "track_label_uuid": null,
        "tracked": true,
        "width": 1.8871731758117676
    },
    {
        "center": {
            "x": -22.663677215576172,
            "y": 50.87507247924805,
            "z": -0.045330822467803955
        },
        "height": 1.639060378074646,
        "label_class": "VEHICLE",
        "length": 4.357492446899414,
        "occlusion": 0,
        "rotation": {
            "w": -0.1080110815077608,
            "x": 0.0,
            "y": 0.0,
            "z": -0.9941496900726389
        },
        "score": 0.11682318896055222,
        "timestamp": 315966380219826000,
        "track_label_uuid": null,
        "tracked": true,
        "width": 1.867071509361267
    },
    {
        "center": {
            "x": 17.9315242767334,
            "y": -30.877925872802734,
            "z": 1.254439353942871
        },
        "height": 1.612240195274353,
        "label_class": "VEHICLE",
        "length": 4.351526737213135,
        "occlusion": 0,
        "rotation": {
            "w": -0.6111357985198426,
            "x": 0.0,
            "y": 0.0,
            "z": -0.7915257644369603
        },
        "score": 0.11659853905439377,
        "timestamp": 315966380219826000,
        "track_label_uuid": null,
        "tracked": true,
        "width": 1.9476754665374756
    },
    {
        "center": {
            "x": -38.90182876586914,
            "y": -23.308870315551758,
            "z": 0.6094556450843811
        },
        "height": 1.5458824634552002,
        "label_class": "VEHICLE",
        "length": 4.416628837585449,
        "occlusion": 0,
        "rotation": {
            "w": 0.7120015597281294,
            "x": 0.0,
            "y": 0.0,
            "z": -0.7021778826940585
        },
        "score": 0.11253167688846588,
        "timestamp": 315966380219826000,
        "track_label_uuid": null,
        "tracked": true,
        "width": 1.823626160621643
    },
    {
        "center": {
            "x": -43.7442741394043,
            "y": -23.503786087036133,
            "z": 0.5147753357887268
        },
        "height": 1.7452282905578613,
        "label_class": "VEHICLE",
        "length": 4.238880157470703,
        "occlusion": 0,
        "rotation": {
            "w": -0.986971438741409,
            "x": 0.0,
            "y": 0.0,
            "z": -0.16089555341498138
        },
        "score": 0.11208457499742508,
        "timestamp": 315966380219826000,
        "track_label_uuid": null,
        "tracked": true,
        "width": 1.9224919080734253
    },
    {
        "center": {
            "x": 21.240888595581055,
            "y": -57.79802322387695,
            "z": 1.9233283996582031
        },
        "height": 1.796419620513916,
        "label_class": "VEHICLE",
        "length": 4.861202239990234,
        "occlusion": 0,
        "rotation": {
            "w": 0.7093397262435804,
            "x": 0.0,
            "y": 0.0,
            "z": -0.7048667624258377
        },
        "score": 0.11171841621398926,
        "timestamp": 315966380219826000,
        "track_label_uuid": null,
        "tracked": true,
        "width": 2.196833848953247
    },
    {
        "center": {
            "x": -71.81694793701172,
            "y": -20.267383575439453,
            "z": 0.8307246565818787
        },
        "height": 1.7368762493133545,
        "label_class": "VEHICLE",
        "length": 4.354984760284424,
        "occlusion": 0,
        "rotation": {
            "w": -0.9921332413596377,
            "x": 0.0,
            "y": 0.0,
            "z": -0.12518638659702166
        },
        "score": 0.11038089543581009,
        "timestamp": 315966380219826000,
        "track_label_uuid": null,
        "tracked": true,
        "width": 1.9288407564163208
    },
    {
        "center": {
            "x": -77.87467956542969,
            "y": -31.62570571899414,
            "z": 0.9380142092704773
        },
        "height": 1.7041683197021484,
        "label_class": "VEHICLE",
        "length": 4.346112251281738,
        "occlusion": 0,
        "rotation": {
            "w": -0.9829673861114578,
            "x": 0.0,
            "y": 0.0,
            "z": -0.1837800800990363
        },
        "score": 0.10935398191213608,
        "timestamp": 315966380219826000,
        "track_label_uuid": null,
        "tracked": true,
        "width": 1.898696780204773
    },
    {
        "center": {
            "x": -22.006168365478516,
            "y": 68.46737670898438,
            "z": -1.1749730110168457
        },
        "height": 1.627671241760254,
        "label_class": "VEHICLE",
        "length": 4.19456672668457,
        "occlusion": 0,
        "rotation": {
            "w": 0.7351854415923432,
            "x": 0.0,
            "y": 0.0,
            "z": -0.6778660387352883
        },
        "score": 0.1087270975112915,
        "timestamp": 315966380219826000,
        "track_label_uuid": null,
        "tracked": true,
        "width": 1.861084222793579
    },
    {
        "center": {
            "x": 20.43347930908203,
            "y": -54.78668975830078,
            "z": 2.0435609817504883
        },
        "height": 1.7872419357299805,
        "label_class": "VEHICLE",
        "length": 4.6482930183410645,
        "occlusion": 0,
        "rotation": {
            "w": 0.7233532793700467,
            "x": 0.0,
            "y": 0.0,
            "z": -0.6904781192945938
        },
        "score": 0.10726157575845718,
        "timestamp": 315966380219826000,
        "track_label_uuid": null,
        "tracked": true,
        "width": 2.104078769683838
    },
    {
        "center": {
            "x": 76.58122253417969,
            "y": 36.393619537353516,
            "z": -0.4083212614059448
        },
        "height": 1.5865199565887451,
        "label_class": "VEHICLE",
        "length": 4.313158988952637,
        "occlusion": 0,
        "rotation": {
            "w": 0.1864021626500249,
            "x": 0.0,
            "y": 0.0,
            "z": -0.9824735282741177
        },
        "score": 0.10721553862094879,
        "timestamp": 315966380219826000,
        "track_label_uuid": null,
        "tracked": true,
        "width": 1.8513109683990479
    },
    {
        "center": {
            "x": 100.93578338623047,
            "y": 57.22780990600586,
            "z": 0.2896043658256531
        },
        "height": 1.70722234249115,
        "label_class": "VEHICLE",
        "length": 4.1865644454956055,
        "occlusion": 0,
        "rotation": {
            "w": -0.983473970585564,
            "x": 0.0,
            "y": 0.0,
            "z": -0.18104957658239718
        },
        "score": 0.10591019690036774,
        "timestamp": 315966380219826000,
        "track_label_uuid": null,
        "tracked": true,
        "width": 1.929108738899231
    },
    {
        "center": {
            "x": -72.42020416259766,
            "y": -34.145626068115234,
            "z": 1.460188388824463
        },
        "height": 1.6223924160003662,
        "label_class": "VEHICLE",
        "length": 4.353866100311279,
        "occlusion": 0,
        "rotation": {
            "w": 0.7325884331694401,
            "x": 0.0,
            "y": 0.0,
            "z": -0.6806718648411617
        },
        "score": 0.10506134480237961,
        "timestamp": 315966380219826000,
        "track_label_uuid": null,
        "tracked": true,
        "width": 1.8902829885482788
    },
    {
        "center": {
            "x": -46.76702117919922,
            "y": -18.028850555419922,
            "z": 0.9237084984779358
        },
        "height": 1.6320043802261353,
        "label_class": "VEHICLE",
        "length": 4.2610273361206055,
        "occlusion": 0,
        "rotation": {
            "w": -0.9890198293026512,
            "x": 0.0,
            "y": 0.0,
            "z": -0.1477828719647668
        },
        "score": 0.10327275842428207,
        "timestamp": 315966380219826000,
        "track_label_uuid": null,
        "tracked": true,
        "width": 1.9128328561782837
    },
    {
        "center": {
            "x": -10.14871597290039,
            "y": 8.382111549377441,
            "z": 0.5865556597709656
        },
        "height": 1.5693771839141846,
        "label_class": "VEHICLE",
        "length": 4.02833366394043,
        "occlusion": 0,
        "rotation": {
            "w": 0.1061413232815613,
            "x": 0.0,
            "y": 0.0,
            "z": -0.9943510544531238
        },
        "score": 0.10323665291070938,
        "timestamp": 315966380219826000,
        "track_label_uuid": null,
        "tracked": true,
        "width": 1.7262481451034546
    },
    {
        "center": {
            "x": -44.36922836303711,
            "y": -6.905768394470215,
            "z": 0.6846068501472473
        },
        "height": 1.659149408340454,
        "label_class": "VEHICLE",
        "length": 4.190223217010498,
        "occlusion": 0,
        "rotation": {
            "w": -0.9822685136489594,
            "x": 0.0,
            "y": 0.0,
            "z": -0.18747951113085404
        },
        "score": 0.10191524773836136,
        "timestamp": 315966380219826000,
        "track_label_uuid": null,
        "tracked": true,
        "width": 1.644058346748352
    },
    {
        "center": {
            "x": 43.619014739990234,
            "y": 24.74437141418457,
            "z": 0.26979702711105347
        },
        "height": 1.739725112915039,
        "label_class": "VEHICLE",
        "length": 4.842378616333008,
        "occlusion": 0,
        "rotation": {
            "w": 0.6700802331558906,
            "x": 0.0,
            "y": 0.0,
            "z": -0.74228867776206
        },
        "score": 0.10128907114267349,
        "timestamp": 315966380219826000,
        "track_label_uuid": null,
        "tracked": true,
        "width": 2.0215442180633545
    },
    {
        "center": {
            "x": -15.477093696594238,
            "y": 58.98004150390625,
            "z": -0.23138213157653809
        },
        "height": 1.6630139350891113,
        "label_class": "VEHICLE",
        "length": 4.2255072593688965,
        "occlusion": 0,
        "rotation": {
            "w": 0.8350099115304034,
            "x": 0.0,
            "y": 0.0,
            "z": -0.5502349022426585
        },
        "score": 0.10102279484272003,
        "timestamp": 315966380219826000,
        "track_label_uuid": null,
        "tracked": true,
        "width": 1.9535949230194092
    },
    {
        "center": {
            "x": -2.8205230236053467,
            "y": -5.119585037231445,
            "z": 0.8761275410652161
        },
        "height": 1.94039785861969,
        "label_class": "PEDESTRIAN",
        "length": 0.7437398433685303,
        "occlusion": 0,
        "rotation": {
            "w": 0.8021240059103522,
            "x": 0.0,
            "y": 0.0,
            "z": -0.5971574994440991
        },
        "score": 0.6547933220863342,
        "timestamp": 315966380219826000,
        "track_label_uuid": null,
        "tracked": true,
        "width": 0.7131492495536804
    },
    {
        "center": {
            "x": 11.28190803527832,
            "y": 21.270885467529297,
            "z": 0.3406938910484314
        },
        "height": 1.84988534450531,
        "label_class": "PEDESTRIAN",
        "length": 0.6654664874076843,
        "occlusion": 0,
        "rotation": {
            "w": 0.7172623096137537,
            "x": 0.0,
            "y": 0.0,
            "z": -0.6968032571734606
        },
        "score": 0.5848519206047058,
        "timestamp": 315966380219826000,
        "track_label_uuid": null,
        "tracked": true,
        "width": 0.6587640047073364
    },
    {
        "center": {
            "x": 9.357040405273438,
            "y": 21.690650939941406,
            "z": 0.2297554612159729
        },
        "height": 1.8601443767547607,
        "label_class": "PEDESTRIAN",
        "length": 0.6751849055290222,
        "occlusion": 0,
        "rotation": {
            "w": 0.8566878706311949,
            "x": 0.0,
            "y": 0.0,
            "z": -0.5158351406344756
        },
        "score": 0.44750547409057617,
        "timestamp": 315966380219826000,
        "track_label_uuid": null,
        "tracked": true,
        "width": 0.6774343252182007
    },
    {
        "center": {
            "x": 11.420357704162598,
            "y": 22.084495544433594,
            "z": 0.33031612634658813
        },
        "height": 1.8453965187072754,
        "label_class": "PEDESTRIAN",
        "length": 0.669051468372345,
        "occlusion": 0,
        "rotation": {
            "w": 0.7170149371445367,
            "x": 0.0,
            "y": 0.0,
            "z": -0.6970578024178598
        },
        "score": 0.429797887802124,
        "timestamp": 315966380219826000,
        "track_label_uuid": null,
        "tracked": true,
        "width": 0.6440414786338806
    },
    {
        "center": {
            "x": 20.75748062133789,
            "y": -5.441908836364746,
            "z": 0.6799445748329163
        },
        "height": 1.770289421081543,
        "label_class": "PEDESTRIAN",
        "length": 0.6607698202133179,
        "occlusion": 0,
        "rotation": {
            "w": 0.18742264532465372,
            "x": 0.0,
            "y": 0.0,
            "z": -0.9822793655674077
        },
        "score": 0.33516886830329895,
        "timestamp": 315966380219826000,
        "track_label_uuid": null,
        "tracked": true,
        "width": 0.8223652243614197
    },
    {
        "center": {
            "x": 12.094274520874023,
            "y": 21.871761322021484,
            "z": 0.3306736350059509
        },
        "height": 1.777551293373108,
        "label_class": "PEDESTRIAN",
        "length": 0.664400577545166,
        "occlusion": 0,
        "rotation": {
            "w": -0.6959528009296114,
            "x": 0.0,
            "y": 0.0,
            "z": -0.7180875287026148
        },
        "score": 0.221115380525589,
        "timestamp": 315966380219826000,
        "track_label_uuid": null,
        "tracked": true,
        "width": 0.6182676553726196
    },
    {
        "center": {
            "x": 14.007394790649414,
            "y": 20.65770149230957,
            "z": 0.20907706022262573
        },
        "height": 1.8570507764816284,
        "label_class": "PEDESTRIAN",
        "length": 0.6598914265632629,
        "occlusion": 0,
        "rotation": {
            "w": 0.9849176631185187,
            "x": 0.0,
            "y": 0.0,
            "z": 0.17302368877456092
        },
        "score": 0.17411158978939056,
        "timestamp": 315966380219826000,
        "track_label_uuid": null,
        "tracked": true,
        "width": 0.718390166759491
    },
    {
        "center": {
            "x": 43.662559509277344,
            "y": 22.312950134277344,
            "z": -0.0199587345123291
        },
        "height": 1.8561959266662598,
        "label_class": "PEDESTRIAN",
        "length": 0.8433464169502258,
        "occlusion": 0,
        "rotation": {
            "w": 0.5711957362563108,
            "x": 0.0,
            "y": 0.0,
            "z": 0.8208138832175118
        },
        "score": 0.1070324257016182,
        "timestamp": 315966380219826000,
        "track_label_uuid": null,
        "tracked": true,
        "width": 0.7807223796844482
    },
    {
        "center": {
            "x": -52.881385803222656,
            "y": -11.78596305847168,
            "z": 0.7811557650566101
        },
        "height": 1.884506106376648,
        "label_class": "PEDESTRIAN",
        "length": 0.7142248153686523,
        "occlusion": 0,
        "rotation": {
            "w": -0.9852010764018025,
            "x": 0.0,
            "y": 0.0,
            "z": -0.1714025643236691
        },
        "score": 0.10532501339912415,
        "timestamp": 315966380219826000,
        "track_label_uuid": null,
        "tracked": true,
        "width": 0.7323455810546875
    },
    {
        "center": {
            "x": 42.802520751953125,
            "y": 22.696550369262695,
            "z": -0.04260993003845215
        },
        "height": 1.8380550146102905,
        "label_class": "PEDESTRIAN",
        "length": 0.8419117331504822,
        "occlusion": 0,
        "rotation": {
            "w": 0.4819294423937963,
            "x": 0.0,
            "y": 0.0,
            "z": 0.8762100276497665
        },
        "score": 0.10056918114423752,
        "timestamp": 315966380219826000,
        "track_label_uuid": null,
        "tracked": true,
        "width": 0.7697777152061462
    }
]